IdeaSearch_fit/__init__.py
IdeaSearch_fit/fitter.py
IdeaSearch_fit/pareto_frontier.py
IdeaSearch_fit/unit_validator.py
IdeaSearch_fit/locales/messages.pot
IdeaSearch_fit/locales/en_US/LC_MESSAGES/messages.mo
IdeaSearch_fit/locales/en_US/LC_MESSAGES/messages.po
IdeaSearch_fit/locales/zh_CN/LC_MESSAGES/messages.mo
IdeaSearch_fit/locales/zh_CN/LC_MESSAGES/messages.po
IdeaSearch_fit/miscellaneous/__init__.py
IdeaSearch_fit/miscellaneous/hello.py
IdeaSearch_fit/utils/__init__.py
IdeaSearch_fit/utils/external.py
IdeaSearch_fit/utils/i18n.py
IdeaSearch_fit/utils/json_tools.py
IdeaSearch_fit/utils/pywheels.py
IdeaSearch_fit/utils/typing.py
ideasearch_fit-0.0.5.1.dist-info/METADATA
ideasearch_fit-0.0.5.1.dist-info/WHEEL
ideasearch_fit-0.0.5.1.dist-info/top_level.txt
ideasearch_fit-0.0.5.1.dist-info/RECORD
