Metadata-Version: 2.1
Name: ideasearch-fit
Version: 0.0.5.1
Summary: Extension of IdeaSearch for data fitting
Home-page: https://github.com/IdeaSearch/IdeaSearch-fit
Author: parkcai
Author-email: sun_retailer@163.com
Requires-Python: >=3.8
Requires-Dist: numpy (>=1.21.0)
Requires-Dist: numexpr (>=2.7.0)
Requires-Dist: pywheels (>=0.7.6.2)
Requires-Dist: IdeaSearch (>=0.1.1)
